nowyou_vstitcher_script_python/__init__.py
nowyou_vstitcher_script_python/start.py
nowyou_vstitcher_script_python/model/__init__.py
nowyou_vstitcher_script_python/tasks/__init__.py
nowyou_vstitcher_script_python/tasks/export_avatar.py
nowyou_vstitcher_script_python/tasks/product_visualization_export.py
nowyou_vstitcher_script_python/utils/__init__.py
nowyou_vstitcher_script_python/utils/utils.py
nowyou_vstitcher_script_python/vstitcher_plugins/__init__.py
nowyou_vstitcher_script_python/vstitcher_plugins/avatar_export/__init__.py
nowyou_vstitcher_script_python/vstitcher_plugins/avatar_export/plugin.json
nowyou_vstitcher_script_python/vstitcher_plugins/avatar_export/resources/__init__.py
nowyou_vstitcher_script_python/vstitcher_plugins/avatar_export/resources/avatar_measurements.json
nowyou_vstitcher_script_python/vstitcher_plugins/avatar_export/resources/avatar_scheme.json
nowyou_vstitcher_script_python/vstitcher_plugins/avatar_export/resources/export_schema.json
nowyou_vstitcher_script_python/vstitcher_plugins/avatar_export/resources/fision.json
nowyou_vstitcher_script_python/vstitcher_plugins/avatar_export/resources/t.py
nowyou_vstitcher_script_python/vstitcher_plugins/avatar_export/src/__init__.py
nowyou_vstitcher_script_python/vstitcher_plugins/avatar_export/src/avatar.py
nowyou_vstitcher_script_python/vstitcher_plugins/product_visualization_export/__init__.py
nowyou_vstitcher_script_python/vstitcher_plugins/product_visualization_export/plugin.json
nowyou_vstitcher_script_python/vstitcher_plugins/product_visualization_export/resources/__init__.py
nowyou_vstitcher_script_python/vstitcher_plugins/product_visualization_export/resources/export_schema.json
nowyou_vstitcher_script_python/vstitcher_plugins/product_visualization_export/src/__init__.py
nowyou_vstitcher_script_python/vstitcher_plugins/product_visualization_export/src/script.py
nowyou_vstitcher_script_python-0.1.49.dist-info/METADATA
nowyou_vstitcher_script_python-0.1.49.dist-info/WHEEL
nowyou_vstitcher_script_python-0.1.49.dist-info/top_level.txt
nowyou_vstitcher_script_python-0.1.49.dist-info/RECORD
