Metadata-Version: 2.1
Name: nowyou-vstitcher-script-python
Version: 0.1.49
Summary: Nowyou VStitcher script python
Home-page: https://bitbucket.org/inventilabs/nowyou-vstitcher-script-python/
Author: Alex Mensak
Author-email: alexander.mensak@ilabs.cz
License: proprietary
Keywords: nowyou python
Platform: UNKNOWN
Classifier: Development Status :: 3 - Alpha
Classifier: Intended Audience :: Developers
Classifier: Topic :: Software Development :: Libraries
Classifier: License :: Other/Proprietary License
Classifier: Programming Language :: Python :: 3
Requires-Python: >=3.6
Requires-Dist: pyautogui
